aiogram_logging/__init__.py
aiogram_logging/logger.py
aiogram_logging/sender.py
aiogram_logging-0.0.1.dist-info/LICENSE
aiogram_logging-0.0.1.dist-info/METADATA
aiogram_logging-0.0.1.dist-info/WHEEL
aiogram_logging-0.0.1.dist-info/top_level.txt
aiogram_logging-0.0.1.dist-info/RECORD
