Metadata-Version: 2.1
Name: aiogram-logging
Version: 0.0.1
Summary: Simplifies sending logs from your bots to DB.
Home-page: https://github.com/dkeysil/aiogram-logging
Author: Dmitry Keysil
Author-email: kl0opa.11@gmail.com
License: MIT
Platform: UNKNOWN
Classifier: Operating System :: OS Independent
Classifier: Intended Audience :: Developers
Classifier: License :: OSI Approved :: MIT License
Classifier: Programming Language :: Python :: 3
Requires-Python: >=3.6
Requires-Dist: aiogram (<3)
Requires-Dist: aioinflux
